acad_extractor.pyd
acad_extractor-1.0.9.dist-info/LICENSE
acad_extractor-1.0.9.dist-info/METADATA
acad_extractor-1.0.9.dist-info/WHEEL
acad_extractor-1.0.9.dist-info/top_level.txt
acad_extractor-1.0.9.dist-info/RECORD
