Metadata-Version: 2.1
Name: acad-extractor
Version: 1.0.9
Summary: A quick tool to extract block attributes and properties from AutoCAD drawings
Author-email: Alexandr Gusev <alphacity@yandex.ru>
License: MIT
Project-URL: Homepage, https://github.com/Alexandr-Gusev/acad-extractor
Keywords: quick,extract,block,attributes,properties,AutoCAD
Classifier: Programming Language :: Python :: 3
Classifier: License :: OSI Approved :: MIT License
Classifier: Operating System :: OS Independent
Requires-Python: >=3.9.9
License-File: LICENSE
